LICENSE
README.md
setup.cfg
setup.py
wc_django_user_checks.egg-info/PKG-INFO
wc_django_user_checks.egg-info/SOURCES.txt
wc_django_user_checks.egg-info/dependency_links.txt
wc_django_user_checks.egg-info/requires.txt
wc_django_user_checks.egg-info/top_level.txt
wcd_user_checks/__init__.py
wcd_user_checks/apps.py
wcd_user_checks/builtins.py
wcd_user_checks/cases.py
wcd_user_checks/client.py
wcd_user_checks/conf.py
wcd_user_checks/discovery.py
wcd_user_checks/dtos.py
wcd_user_checks/exceptions.py
wcd_user_checks/globals.py
wcd_user_checks/models.py
wcd_user_checks/query.py
wcd_user_checks/registry.py
wcd_user_checks/signals.py
wcd_user_checks/utils.py
wcd_user_checks/admin/__init__.py
wcd_user_checks/admin/filters.py
wcd_user_checks/admin/forms.py
wcd_user_checks/admin/inlines.py
wcd_user_checks/admin/mixins.py
wcd_user_checks/admin/modeladmin.py
wcd_user_checks/contrib/__init__.py
wcd_user_checks/contrib/drf/__init__.py
wcd_user_checks/contrib/drf/apps.py
wcd_user_checks/migrations/0001_initial.py
wcd_user_checks/migrations/0002_auto_20210624_1417.py
wcd_user_checks/migrations/__init__.py